<?xml version="1.0" encoding="UTF-8" ?>
<XMLDB PATH="mod/richmedia/db" VERSION="20111012" COMMENT="XMLDB file for Moodle mod/richmedia"
       xmlns:xsi="http://www.w3.org/2001/XMLSchema-instance"
       xsi:noNamespaceSchemaLocation="../../../lib/xmldb/xmldb.xsd"
>
    <TABLES>
        <TABLE NAME="richmedia" COMMENT="each table is one RICHMEDIA module and its configuration" NEXT="richmedia_track">
            <FIELDS>
                <FIELD NAME="id" TYPE="int" LENGTH="10" NOTNULL="true" UNSIGNED="true" SEQUENCE="true"/>
                <FIELD NAME="course" TYPE="int" LENGTH="10" NOTNULL="true" UNSIGNED="true" DEFAULT="0" SEQUENCE="false"/>
                <FIELD NAME="name" TYPE="char" LENGTH="255" NOTNULL="true" SEQUENCE="false"/>
                <FIELD NAME="referenceslides" TYPE="char" LENGTH="255" NOTNULL="true" SEQUENCE="false"/>
                <FIELD NAME="referencesvideo" TYPE="char" LENGTH="255" NOTNULL="true" SEQUENCE="false"/>
                <FIELD NAME="referencesfond" TYPE="char" LENGTH="255" NOTNULL="true" SEQUENCE="false"/>
                <FIELD NAME="referencesxml" TYPE="char" LENGTH="255" NOTNULL="true" SEQUENCE="false"/>
                <FIELD NAME="referencessynchro" TYPE="char" LENGTH="255" NOTNULL="true" SEQUENCE="false"/>
                <FIELD NAME="sha1hash" TYPE="char" LENGTH="40" NOTNULL="false" SEQUENCE="false" COMMENT="package content or ext path hash"/>
                <FIELD NAME="intro" TYPE="text" LENGTH="small" NOTNULL="true" SEQUENCE="false"/>
                <FIELD NAME="introformat" TYPE="int" LENGTH="4" NOTNULL="true" UNSIGNED="true" DEFAULT="0" SEQUENCE="false"/>
                <FIELD NAME="width" TYPE="int" LENGTH="10" NOTNULL="true" UNSIGNED="true" DEFAULT="100" SEQUENCE="false"/>
                <FIELD NAME="height" TYPE="int" LENGTH="10" NOTNULL="true" UNSIGNED="true" DEFAULT="600" SEQUENCE="false"/>
                <FIELD NAME="theme" TYPE="char" LENGTH="255" NOTNULL="true" SEQUENCE="false"/>
                <FIELD NAME="html5" TYPE="int" LENGTH="4" NOTNULL="true" UNSIGNED="true" DEFAULT="0" SEQUENCE="false"/>
                <FIELD NAME="font" TYPE="char" LENGTH="255" NOTNULL="true" SEQUENCE="false"/>
                <FIELD NAME="fontcolor" TYPE="char" LENGTH="8" NOTNULL="true" UNSIGNED="true" DEFAULT="0" SEQUENCE="false"/>
                <FIELD NAME="defaultview" TYPE="int" LENGTH="4" NOTNULL="true" UNSIGNED="true" DEFAULT="0" SEQUENCE="false"/>
                <FIELD NAME="autoplay" TYPE="int" LENGTH="4" NOTNULL="true" UNSIGNED="true" DEFAULT="0" SEQUENCE="false"/>
                <FIELD NAME="presentor" TYPE="char" LENGTH="255" NOTNULL="true" SEQUENCE="false"/>
                <FIELD NAME="keywords" TYPE="char" LENGTH="255" NOTNULL="true" SEQUENCE="false"/>
                <FIELD NAME="quizid" TYPE="int" LENGTH="10" NOTNULL="true" SEQUENCE="false" />
                <FIELD NAME="recovery" TYPE="int" LENGTH="10" NOTNULL="true" SEQUENCE="false" DEFAULT="0"/>
                <FIELD NAME="videourl" TYPE="char" LENGTH="255" SEQUENCE="false"/>
                <FIELD NAME="referencessubtitles" TYPE="char" LENGTH="255" SEQUENCE="false"/>
            </FIELDS>
            <KEYS>
                <KEY NAME="primary" TYPE="primary" FIELDS="id"/>
            </KEYS>
            <INDEXES>
                <INDEX NAME="course" UNIQUE="false" FIELDS="course"/>
            </INDEXES>
        </TABLE>
        <TABLE NAME="richmedia_track" COMMENT="to track Rich medias" PREVIOUS="richmedia">
            <FIELDS>
                <FIELD NAME="id" TYPE="int" LENGTH="10" NOTNULL="true" UNSIGNED="true" SEQUENCE="true"/>
                <FIELD NAME="userid" TYPE="int" LENGTH="10" NOTNULL="true" UNSIGNED="true" DEFAULT="0" SEQUENCE="false"/>
                <FIELD NAME="richmediaid" TYPE="int" LENGTH="10" NOTNULL="true" UNSIGNED="false" DEFAULT="0" SEQUENCE="false"/>
                <FIELD NAME="attempt" TYPE="int" LENGTH="10" NOTNULL="true" UNSIGNED="true" DEFAULT="1" SEQUENCE="false"/>
                <FIELD NAME="start" TYPE="int" LENGTH="10" NOTNULL="true" UNSIGNED="true" DEFAULT="0" SEQUENCE="false"/>
                <FIELD NAME="last" TYPE="int" LENGTH="10" NOTNULL="true" UNSIGNED="true" DEFAULT="0" SEQUENCE="false"/>
                <FIELD NAME="time" TYPE="int" LENGTH="10" NOTNULL="true" UNSIGNED="true" DEFAULT="0" SEQUENCE="false"/>
            </FIELDS>
            <KEYS>
                <KEY NAME="primary" TYPE="primary" FIELDS="id" NEXT="richmediaid"/>
                <KEY NAME="richmediaid" TYPE="foreign" FIELDS="richmediaid" REFTABLE="richmedia" REFFIELDS="id"/>
            </KEYS>
            <INDEXES>
                <INDEX NAME="userid-richmediaid" UNIQUE="true" FIELDS="userid, richmediaid"/>
                <INDEX NAME="userid" UNIQUE="false" FIELDS="userid"/>
            </INDEXES>
        </TABLE>
    </TABLES>
</XMLDB>
